tuck/__init__.py
tuck/__main__.py
tuck/ast.py
tuck/cli.py
tuck/editing.py
tuck/exceptions.py
tuck/main.py
tuck/py.typed
tuck/wrappers.py
tuck-0.2.5.dist-info/licenses/LICENSE
tuck-0.2.5.dist-info/METADATA
tuck-0.2.5.dist-info/WHEEL
tuck-0.2.5.dist-info/top_level.txt
tuck-0.2.5.dist-info/RECORD
