Metadata-Version: 2.4
Name: tuck
Version: 0.2.5
Summary: Semi-automated Python formatting.
Home-page: https://github.com/PeterJCLaw/tuck
Author: Peter Law
Author-email: PeterJCLaw@gmail.com
License: Apache 2.0
Project-URL: Issue tracker, https://github.com/PeterJCLaw/tuck/issues
Classifier: Development Status :: 2 - Pre-Alpha
Classifier: Environment :: Console
Classifier: Natural Language :: English
Classifier: Operating System :: OS Independent
Classifier: Programming Language :: Python
Classifier: Programming Language :: Python :: 3 :: Only
Classifier: Programming Language :: Python :: 3.7
Classifier: Programming Language :: Python :: 3.8
Classifier: Programming Language :: Python :: 3.9
Classifier: Programming Language :: Python :: 3.10
Classifier: Programming Language :: Python :: 3.11
Classifier: Programming Language :: Python :: 3.12
Classifier: Programming Language :: Python :: 3.13
Classifier: Topic :: Software Development
Requires-Python: >=3.7
License-File: LICENSE
Requires-Dist: asttokens<4,>=2
Dynamic: author
Dynamic: author-email
Dynamic: classifier
Dynamic: description
Dynamic: description-content-type
Dynamic: home-page
Dynamic: license
Dynamic: license-file
Dynamic: project-url
Dynamic: requires-dist
Dynamic: requires-python
Dynamic: summary
